hdi1/__init__.py
hdi1/__main__.py
hdi1/nf4.py
hdi1/web.py
hdi1/models/attention.py
hdi1/models/attention_processor.py
hdi1/models/embeddings.py
hdi1/models/moe.py
hdi1/models/transformers/transformer_hidream_image.py
hdi1/pipelines/hidream_image/pipeline_hidream_image.py
hdi1/pipelines/hidream_image/pipeline_output.py
hdi1/schedulers/flash_flow_match.py
hdi1/schedulers/fm_solvers_unipc.py
hdi1-1.0.4.dist-info/licenses/LICENSE
hdi1-1.0.4.dist-info/METADATA
hdi1-1.0.4.dist-info/WHEEL
hdi1-1.0.4.dist-info/top_level.txt
hdi1-1.0.4.dist-info/RECORD
