Metadata-Version: 2.4
Name: hdi1
Version: 1.0.4
Summary: HiDream-I1 is a new open-source image generative foundation model with 17B parameters that achieves state-of-the-art image generation quality within seconds.
Project-URL: Homepage, https://github.com/hykilpikonna/HiDream-I1-nf4
Project-URL: Repository, https://github.com/hykilpikonna/HiDream-I1-nf4
Project-URL: Issues, https://github.com/hykilpikonna/HiDream-I1-nf4/issues
Requires-Python: >=3.10
License-File: LICENSE
Requires-Dist: accelerate>=1.2.1
Requires-Dist: bitsandbytes>=0.45.5
Requires-Dist: datasets>=3.5.0
Requires-Dist: device-smi>=0.4.1
Requires-Dist: diffusers>=0.32.1
Requires-Dist: einops>=0.7.0
Requires-Dist: flash-attn>=2.7.0
Requires-Dist: gptqmodel>=2.2.0
Requires-Dist: gradio>=5.24.0
Requires-Dist: hf-transfer>=0.1.9
Requires-Dist: logbar>=0.0.4
Requires-Dist: optimum>=1.24.0
Requires-Dist: pillow>=11.1.0
Requires-Dist: protobuf>=6.30.2
Requires-Dist: sentencepiece>=0.2.0
Requires-Dist: setuptools>=78.1.0
Requires-Dist: threadpoolctl>=3.6.0
Requires-Dist: tokenicer>=0.0.4
Requires-Dist: torch>=2.5.1
Requires-Dist: torchvision>=0.20.1
Requires-Dist: transformers>=4.47.1
Dynamic: license-file
